AIBoost.cpython-310-x86_64-linux-gnu.so
AIBoost-0.0.1.dist-info/METADATA
AIBoost-0.0.1.dist-info/WHEEL
AIBoost-0.0.1.dist-info/top_level.txt
AIBoost-0.0.1.dist-info/RECORD
